README.md
setup.cfg
setup.py
torchcut/__init__.py
torchcut.egg-info/PKG-INFO
torchcut.egg-info/SOURCES.txt
torchcut.egg-info/dependency_links.txt
torchcut.egg-info/requires.txt
torchcut.egg-info/top_level.txt