Metadata-Version: 1.0
Name: torchcut
Version: 0.1.2
Summary: Shortcut for common PyTorch related imports.
Home-page: UNKNOWN
Author: Kristian Klemon
Author-email: kristian.klemon@gmail.com
License: UNKNOWN
Platform: UNKNOWN
